{
  "meta": {
    "description": "2026-05-21 update",
    "weeklyUpdateTimestamp": 1779357600,
    "hotfixUpdateTimestamp": 1779372553
  },
  "categories": {
    "hair": [
      "轻松游戏女发",
      "轻松游戏男发",
      "涟生花影男发",
      "涟生花影女发",
      "小兔茶杯坊男发",
      "小兔茶杯坊女发",
      "小画家女发",
      "小画家男发",
      "活力马卡龙男发",
      "活力马卡龙女发",
      "暖香漫步女发",
      "暖香漫步男发",
      "晴日教室女发",
      "晴日教室男发"
    ],
    "hats": [
      "小兔茶杯坊男耳朵",
      "小兔茶杯坊女耳朵",
      "暖香漫步头饰"
    ],
    "glas": [],
    "mask": [
      "涟生花影发饰",
      "暖香漫步眼镜"
    ],
    "bear": [],
    "coat": [],
    "clot": [],
    "cset": [
      "轻松游戏女装",
      "轻松游戏男装",
      "涟生花影男装",
      "涟生花影女装",
      "小兔茶杯坊男装",
      "小兔茶杯坊女装",
      "小画家女装",
      "小画家男装",
      "活力马卡龙男装",
      "活力马卡龙女装",
      "暖香漫步女装",
      "暖香漫步男装",
      "晴日教室女装",
      "晴日教室男装"
    ],
    "pant": [],
    "wing": []
  }
}