{
  "m_hats027.png": "蓝色礼帽",
  "m_hats031.png": "男保镖黑色礼帽",
  "m_hats033.png": "医生头镜",
  "m_hats036.png": "博士帽",
  "m_hats102.png": "彬彬雅士帽",
  "m_hats103.png": "黑色鸭舌帽",
  "m_hats104.png": "复古摩卡帽",
  "m_hats105.png": "夜叉红角",
  "m_hats1057.png": "甜心猫猫拳男猫耳",
  "m_hats110.png": "红炎礼帽",
  "m_hats1107.png": "惬意一夏男帽",
  "m_hats118.png": "绿野冲锋帽",
  "m_hats121.png": "战士头盔",
  "m_hats122.png": "布衣红色包头",
  "m_hats124.png": "洛奇小草帽",
  "m_hats125.png": "狮奥弥耳",
  "m_hats127.png": "赤牛魔王角",
  "m_hats1284.png": "恋感偶像男头饰",
  "m_hats132.png": "浣浣熊面具",
  "m_hats136.png": "冰爵礼帽",
  "m_hats1381.png": "红丝带蛋糕发卡",
  "m_hats139.png": "青衣头饰",
  "m_hats140.png": "绅士王子礼帽",
  "m_hats142.png": "恶魔骑士帽",
  "m_hats144.png": "何军军帽",
  "m_hats147.png": "骷髅牛角帽",
  "m_hats148.png": "嘻哈小鬼帽",
  "m_hats149.png": "南瓜魔法帽",
  "m_hats152.png": "冰心礼帽",
  "m_hats155.png": "波兰头巾",
  "m_hats156.png": "玛尼小礼帽",
  "m_hats159.png": "圣诞小雪人",
  "m_hats167.png": "圣诞帽",
  "m_hats170.png": "犀利黑棉帽",
  "m_hats173.png": "星夜王冠",
  "m_hats174.png": "帝释珠冠",
  "m_hats179.png": "泉泽发髻",
  "m_hats181.png": "冥炎王冠",
  "m_hats183.png": "爱斯基摩男帽",
  "m_hats187.png": "顶戴花翎",
  "m_hats188.png": "皇帝帽",
  "m_hats190.png": "叮当蓝蓝帽",
  "m_hats192.png": "乐动耳麦",
  "m_hats193.png": "寒冰礼帽",
  "m_hats195.png": "随风警官帽",
  "m_hats196.png": "基德礼帽",
  "m_hats197.png": "衙役帽",
  "m_hats200.png": "占卜小熊",
  "m_hats209.png": "棒球帽",
  "m_hats210.png": "买买提帽",
  "m_hats213.png": "夏日运动帽",
  "m_hats214.png": "发呆浣熊帽",
  "m_hats216.png": "魔法师犄角",
  "m_hats222.png": "银光皓月头盔",
  "m_hats223.png": "童话小礼帽",
  "m_hats226.png": "嘻哈红樱帽",
  "m_hats228.png": "爱心配饰帽",
  "m_hats230.png": "小鹦鹉礼帽",
  "m_hats234.png": "藏蓝星星帽",
  "m_hats236.png": "幽灵南瓜头饰",
  "m_hats238.png": "蓝色风铃配饰",
  "m_hats239.png": "香槟球球帽",
  "m_hats243.png": "樱红耳暖",
  "m_hats244.png": "雪夜星斗帽",
  "m_hats246.png": "折耳兔（男）",
  "m_hats251.png": "金龙角（男）",
  "m_hats252.png": "栗色龙角（男）",
  "m_hats254.png": "机械帽",
  "m_hats256.png": "状元帽",
  "m_hats258.png": "宝石王冠",
  "m_hats259.png": "十字皇冠",
  "m_hats264.png": "爵士礼帽",
  "m_hats265.png": "浪漫歌手帽",
  "m_hats266.png": "仔仔立耳",
  "m_hats267.png": "布带礼帽",
  "m_hats271.png": "冬雪帽",
  "m_hats273.png": "小蚁哥",
  "m_hats275.png": "卷尾喵喵",
  "m_hats277.png": "猫头鹰精灵",
  "m_hats280.png": "兔兔垂耳",
  "m_hats283.png": "熊熊布偶男帽",
  "m_hats285.png": "蓝星机车帽",
  "m_hats288.png": "恶魔金角",
  "m_hats291.png": "天使光环",
  "m_hats297.png": "蔚蓝绅士礼帽",
  "m_hats299.png": "云豆",
  "m_hats301.png": "果酱多拿滋帽子",
  "m_hats304.png": "沐雨学士帽",
  "m_hats309.png": "小老鼠头套",
  "m_hats310.png": "蓝玉发冠",
  "m_hats312.png": "蓝边鸭舌帽",
  "m_hats314.png": "条纹贝雷帽",
  "m_hats316.png": "萌犬耳",
  "m_hats317.png": "写意江湖",
  "m_hats319.png": "巫灵黑角帽男",
  "m_hats324.png": "玻璃泡泡",
  "m_hats329.png": "驯鹿暖冬帽",
  "m_hats331.png": "叮咚圣诞帽",
  "m_hats333.png": "萌猴暖冬帽（男）",
  "m_hats335.png": "幸福男帽",
  "m_hats337.png": "绿叶",
  "m_hats338.png": "腹黑萌马帽",
  "m_hats341.png": "唱歌的菠萝帽",
  "m_hats345.png": "浣熊趴趴顶（男）",
  "m_hats347.png": "白色薄荷皇冠",
  "m_hats348.png": "慕斯礼帽",
  "m_hats350.png": "春暖花开（男）",
  "m_hats352.png": "榛果礼帽",
  "m_hats354.png": "学院黑礼帽",
  "m_hats356.png": "萌叽加个油",
  "m_hats359.png": "天堂之爱",
  "m_hats362.png": "时光旅帽",
  "m_hats363.png": "蓝莓果礼帽",
  "m_hats365.png": "玫瑰丝带礼帽",
  "m_hats367.png": "童梦米奇发饰",
  "m_hats368.png": "浪漫紫薰礼帽",
  "m_hats370.png": "喵咪音乐耳麦",
  "m_hats372.png": "士兵迷彩头盔",
  "m_hats376.png": "银缘花冠",
  "m_hats377.png": "金缘花冠",
  "m_hats378.png": "钻石缘花冠",
  "m_hats382.png": "炸弹狂人帽（男）",
  "m_hats384.png": "猫叔",
  "m_hats386.png": "酒鬼帽（男）",
  "m_hats388.png": "鹦鹉咕咕",
  "m_hats391.png": "雪人头罩（男）",
  "m_hats394.png": "雪狼男帽",
  "m_hats396.png": "圣诞男帽",
  "m_hats397.png": "可爱折耳",
  "m_hats401.png": "世纪婚礼礼帽",
  "m_hats402.png": "耳暖",
  "m_hats404.png": "汤圆约会男帽",
  "m_hats409.png": "氧气男帽",
  "m_hats413.png": "魅蓝骑士帽饰",
  "m_hats416.png": "斯比折耳帽（男）",
  "m_hats419.png": "小可萌帽（男）",
  "m_hats421.png": "妖冶明星男帽",
  "m_hats422.png": "在么~",
  "m_hats424.png": "蔚蓝海岸礼帽",
  "m_hats426.png": "清夏圆礼帽",
  "m_hats428.png": "嘻哈潮帽",
  "m_hats432.png": "叮叮当当兔",
  "m_hats435.png": "旋转木马男帽",
  "m_hats437.png": "小王子礼帽",
  "m_hats440.png": "AH婚礼红毯礼帽",
  "m_hats445.png": "叮当男帽",
  "m_hats449.png": "古典深秋毛绒帽",
  "m_hats450.png": "黑色燕尾服小礼帽",
  "m_hats451.png": "盼盼男帽",
  "m_hats454.png": "青竹发饰",
  "m_hats457.png": "蓝魅男装礼帽",
  "m_hats462.png": "粉色羊毛耳罩",
  "m_hats464.png": "草莓蜜糖派男发饰",
  "m_hats468.png": "斗篷小帽",
  "m_hats470.png": "小画家男帽",
  "m_hats473.png": "宫廷萌兔礼帽",
  "m_hats474.png": "奥利奥男帽",
  "m_hats477.png": "紫爵皇冠",
  "m_hats478.png": "蓝领结礼帽",
  "m_hats479.png": "清凉贝雷帽",
  "m_hats480.png": "清凉T帽",
  "m_hats482.png": "月光骑士发饰",
  "m_hats494.png": "樱之巫师帽",
  "m_hats495.png": "士兵高帽",
  "m_hats500.png": "满天星墨镜",
  "m_hats504.png": "衣袂发饰",
  "m_hats506.png": "腾讯企鹅帽",
  "m_hats508.png": "乐高发饰",
  "m_hats512.png": "动感炫蓝耳机",
  "m_hats516.png": "月明星稀帽子",
  "m_hats518.png": "花样男孩帽子",
  "m_hats521.png": "波斯帽饰",
  "m_hats525.png": "瑰丽乐园狗耳",
  "m_hats532.png": "糖心蜜果小礼帽",
  "m_hats533.png": "南北极蝶舞礼帽",
  "m_hats534.png": "南北极豆豆发饰",
  "m_hats536.png": "南北极星点礼帽",
  "m_hats539.png": "南北极紫蝶礼帽",
  "m_hats544.png": "飘逸阴阳师帽",
  "m_hats548.png": "瞌睡兔兔男帽",
  "m_hats550.png": "天秤星语男帽",
  "m_hats554.png": "咔恰礼帽",
  "m_hats555.png": "南瓜蔷薇男巫帽",
  "m_hats562.png": "天蝎物语礼帽",
  "m_hats563.png": "摇滚小哈男头巾",
  "m_hats564.png": "萌兔游乐园男帽",
  "m_hats567.png": "流星天使环",
  "m_hats569.png": "精灵鼠发耳",
  "m_hats575.png": "扑克男帽",
  "m_hats578.png": "星星糖果发饰",
  "m_hats582.png": "犬神男耳朵",
  "m_hats583.png": "鸟笼男帽",
  "m_hats586.png": "十字路口男帽",
  "m_hats588.png": "倾心紫颜男耳",
  "m_hats594.png": "羊咩咩帽（男）",
  "m_hats597.png": "绿萝男帽",
  "m_hats600.png": "拿小锤锤",
  "m_hats602.png": "草莓软糖头饰",
  "m_hats605.png": "彩色铅笔（男）",
  "m_hats607.png": "蘑蘑男头饰",
  "m_hats610.png": "焦糖男帽",
  "m_hats613.png": "森林谜纱男发饰",
  "m_hats615.png": "蛋糕派对西装男头饰",
  "m_hats616.png": "纸牌王冠",
  "m_hats619.png": "魔灵宿主头饰",
  "m_hats621.png": "绅士兔男帽",
  "m_hats623.png": "星宿使徒男头饰",
  "m_hats629.png": "糖果男孩帽子",
  "m_hats631.png": "尤克里里男头饰",
  "m_hats633.png": "星途发圈",
  "m_hats644.png": "普罗旺斯男头饰",
  "m_hats647.png": "节日气球小蓝鲸",
  "m_hats650.png": "端午节男头饰",
  "m_hats652.png": "叮咚喵喵耳饰",
  "m_hats657.png": "假日沙滩男头饰",
  "m_hats661.png": "纯色花嫁男帽",
  "m_hats662.png": "冰雪兔发饰（男）",
  "m_hats665.png": "清新果茶男头饰",
  "m_hats667.png": "香橙蛋糕男头饰",
  "m_hats669.png": "夏日旅行记男头饰",
  "m_hats673.png": "扑克兔男帽",
  "m_hats674.png": "春意盎然男帽",
  "m_hats678.png": "企鹅水手男帽",
  "m_hats679.png": "冷凝西瓜帽",
  "m_hats690.png": "霜糖蛋糕奶油",
  "m_hats695.png": "赫赤蝙蝠男帽",
  "m_hats697.png": "狐丸阴阳师男头饰",
  "m_hats705.png": "嘻嘻哈哈男帽"
}
