{
  "f_cset001.png": "女生泳装",
  "f_cset003.png": "女亲卫队套装",
  "f_cset004.png": "蝴蝶结套装",
  "f_cset005.png": "青春情侣女装",
  "f_cset006.png": "粉色回忆女装",
  "f_cset007.png": "水瓶座女装",
  "f_cset008.png": "双鱼座女装",
  "f_cset009.png": "牡羊座女装",
  "f_cset010.png": "金牛座女装",
  "f_cset011.png": "双子座女装",
  "f_cset012.png": "巨蟹座女装",
  "f_cset013.png": "狮子座女装",
  "f_cset014.png": "处女座女装",
  "f_cset015.png": "天秤座女装",
  "f_cset016.png": "蝎子座女装",
  "f_cset017.png": "射手座女装",
  "f_cset018.png": "摩羯座女装",
  "f_cset020.png": "贵族礼服",
  "f_cset021.png": "火影小樱套装",
  "f_cset022.png": "火影雏田套装",
  "f_cset023.png": "魔术师女装",
  "f_cset024.png": "恶魔女套装",
  "f_cset025.png": "火影手鞠套装",
  "f_cset026.png": "天使女套装",
  "f_cset027.png": "夏日女套装",
  "f_cset028.png": "小鬼当家女套装",
  "f_cset029.png": "女生粉色睡衣",
  "f_cset030.png": "女医生套装",
  "f_cset031.png": "女护士套装",
  "f_cset032.png": "咖啡店女服务生套装",
  "f_cset033.png": "酒店女服务员套装",
  "f_cset034.png": "女主持人晚装",
  "f_cset035.png": "女保镖迷彩装",
  "f_cset036.png": "女主持人礼服",
  "f_cset037.png": "职业保镖女装",
  "f_cset038.png": "樱姬套装",
  "f_cset039.png": "神职女套装一",
  "f_cset040.png": "女教师套装一",
  "f_cset041.png": "女教师套装二",
  "f_cset042.png": "神职套装二",
  "f_cset043.png": "女美发师套装一",
  "f_cset044.png": "女美发师套装二",
  "f_cset045.png": "女军人套装",
  "f_cset046.png": "女警察套装",
  "f_cset047.png": "皇后金冠女款",
  "f_cset048.png": "朱丽叶套装",
  "f_cset049.png": "爱丽丝套装",
  "f_cset050.png": "田园之旅（女）",
  "f_cset051.png": "神秘星占套装",
  "f_cset052.png": "开心牧场",
  "f_cset053.png": "幻紫魔法(女)",
  "f_cset054.png": "俏皮青春女套装",
  "f_cset055.png": "粉色糖心套装",
  "f_cset056.png": "靓丽朋克女套装",
  "f_cset057.png": "格格套装",
  "f_cset058.png": "粉色甜美雪融套装",
  "f_cset062.png": "猫猫套装",
  "f_cset063.png": "福神女套装",
  "f_cset064.png": "帅气热辣情侣装（女）",
  "f_cset065.png": "橙色炫彩婚纱",
  "f_cset066.png": "白色圣洁婚纱",
  "f_cset067.png": "虎年财神女套装",
  "f_cset068.png": "粉色婚纱",
  "f_cset069.png": "无袖红裙朋克套装",
  "f_cset070.png": "碧荷清爽套装",
  "f_cset071.png": "狮头（女）",
  "f_cset072.png": "狮尾（女）",
  "f_cset073.png": "典雅紫凝套装",
  "f_cset074.png": "红艳黑魅套装",
  "f_cset075.png": "眼镜芭比",
  "f_cset076.png": "樱红点点",
  "f_cset077.png": "小天鹅泳圈套装",
  "f_cset078.png": "青蛙泳圈女套装",
  "f_cset079.png": "丝带天使套装",
  "f_cset080.png": "巴西足球宝贝",
  "f_cset081.png": "阿根廷足球宝贝",
  "f_cset082.png": "德国足球宝贝",
  "f_cset083.png": "西班牙足球宝贝",
  "f_cset084.png": "草莓芭比套装",
  "f_cset085.png": "兔耳御姐套装",
  "f_cset086.png": "女记者套装一",
  "f_cset087.png": "女记者套装二",
  "f_cset088.png": "绿衣小女仆",
  "f_cset089.png": "高贵皇后A",
  "f_cset090.png": "圣女战士",
  "f_cset091.png": "长裙圣女",
  "f_cset092.png": "短裙圣女",
  "f_cset093.png": "优雅女士",
  "f_cset094.png": "贵族女士",
  "f_cset095.png": "贵族皇后B",
  "f_cset097.png": "弥兰莎丽",
  "f_cset098.png": "雪比莉咪",
  "f_cset099.png": "波灵莉喵",
  "f_cset100.png": "织女套装",
  "f_cset101.png": "假面咕咕兔",
  "f_cset102.png": "吉拉宠宠",
  "f_cset103.png": "尼嘟幽蔓套裙",
  "f_cset104.png": "兰蝶幻彩套裙",
  "f_cset105.png": "青青呱呱裙",
  "f_cset106.png": "梦幻蝶蝶裙",
  "f_cset1063.png": "雨落蛙蛙（女）",
  "f_cset107.png": "蓝色星星裙",
  "f_cset108.png": "红奇粉粉裙",
  "f_cset109.png": "粉粉波喱(租)",
  "f_cset110.png": "青青绵绵(租)",
  "f_cset111.png": "小红帽(租)",
  "f_cset114.png": "图图兔(租)",
  "f_cset115.png": "溜溜粉裙(租)",
  "f_cset116.png": "粉色天使心(租)",
  "f_cset117.png": "甜甜圈圈(租)",
  "f_cset118.png": "冰冰波比裙",
  "f_cset119.png": "蝙蝠魔女",
  "f_cset120.png": "绅士公主套装",
  "f_cset121.png": "蝉月套装",
  "f_cset1214.png": "狂奔猪猪（女）",
  "f_cset122.png": "萌动春丽裙",
  "f_cset123.png": "草莓糖果裙",
  "f_cset124.png": "缤纷星星裙",
  "f_cset125.png": "黑嘟嘟小女王",
  "f_cset126.png": "清凉短裙(租)",
  "f_cset127.png": "拉丝金奇(租)",
  "f_cset128.png": "紫蝴蝶套裙",
  "f_cset129.png": "喜美绘套装",
  "f_cset130.png": "鼓鼓绵绵裙",
  "f_cset131.png": "菲灵套装",
  "f_cset132.png": "苏格兰花边裙",
  "f_cset133.png": "王朝马汉（女）",
  "f_cset134.png": "张龙赵虎（女）",
  "f_cset135.png": "衙役（女）",
  "f_cset1367.png": "奶昔泡泡（女）",
  "f_cset137.png": "展昭（女）",
  "f_cset138.png": "公孙策（女）",
  "f_cset139.png": "包青天（女）",
  "f_cset140.png": "米修兔兔裙",
  "f_cset141.png": "囚犯（女）",
  "f_cset142.png": "哔哔圣诞套裙",
  "f_cset143.png": "草莓蓝蓝裙",
  "f_cset144.png": "飘盈绵绵裙",
  "f_cset145.png": "圣诞套裙",
  "f_cset146.png": "卯兔吉祥女套装",
  "f_cset147.png": "莹雪飘飘套装",
  "f_cset148.png": "卡咪梦露套装",
  "f_cset149.png": "樱花润曦套装",
  "f_cset150.png": "蓝莓之兔",
  "f_cset151.png": "蛋糕芭比",
  "f_cset152.png": "淡蓝花语婚纱",
  "f_cset153.png": "爱斯基摩女套装",
  "f_cset154.png": "粉彩蓝幂裙",
  "f_cset155.png": "玫瑰小姐",
  "f_cset156.png": "宫廷秋菊装",
  "f_cset157.png": "宫廷梅芳套装",
  "f_cset158.png": "宫廷春香套装",
  "f_cset159.png": "樱花粉蝶",
  "f_cset160.png": "魅影之舞",
  "f_cset161.png": "旗袍雾纱裙",
  "f_cset162.png": "咪乖猫猫",
  "f_cset163.png": "苏格草草裙",
  "f_cset164.png": "印第酋酋女",
  "f_cset1645.png": "粉裘枫糖女装",
  "f_cset165.png": "克莱尔黑裙",
  "f_cset166.png": "乔乔西红裙",
  "f_cset167.png": "糖果少女",
  "f_cset168.png": "海盗少女",
  "f_cset169.png": "宫廷王妃",
  "f_cset170.png": "紫云碧波套装",
  "f_cset171.png": "修身翠绿黑裙",
  "f_cset172.png": "魔法少女套装",
  "f_cset173.png": "黄莺鸣鸣套装",
  "f_cset174.png": "绿荷小熊套装",
  "f_cset175.png": "淡雅青青梦",
  "f_cset176.png": "粉粉梦露",
  "f_cset177.png": "苹果兜兜",
  "f_cset178.png": "粉色日风裙",
  "f_cset179.png": "蝙蝠魔导师",
  "f_cset180.png": "水果糖糖兔",
  "f_cset181.png": "草莓奶昔",
  "f_cset182.png": "夏香百合",
  "f_cset183.png": "星星飘蓝裙",
  "f_cset1832.png": "抱抱熊女装",
  "f_cset184.png": "堕天使恋裙",
  "f_cset185.png": "疯狂女科学家",
  "f_cset186.png": "星星萝莉裙",
  "f_cset187.png": "清凉运动套装",
  "f_cset188.png": "薄雾纱裙",
  "f_cset189.png": "牛仔背带裤套装",
  "f_cset190.png": "樱光灿烂",
  "f_cset191.png": "复古墨绿裙",
  "f_cset192.png": "菇菇七彩裙",
  "f_cset193.png": "黑白色玫瑰套裙",
  "f_cset1938.png": "心碎信号女装",
  "f_cset194.png": "桐乃套裙",
  "f_cset195.png": "月影飞仙套装",
  "f_cset196.png": "冰晶清凉裙",
  "f_cset197.png": "雾色和服",
  "f_cset198.png": "英伦莉莉安裙",
  "f_cset199.png": "蔷薇吉他手",
  "f_cset200.png": "灯笼小樱桃",
  "f_cset201.png": "唯美空姐套装",
  "f_cset202.png": "樱红和服裙",
  "f_cset203.png": "洋洋伞斗篷套装",
  "f_cset204.png": "南瓜糖果套装",
  "f_cset205.png": "海洋女船长",
  "f_cset206.png": "安娜公主套装",
  "f_cset208.png": "蓝色花语",
  "f_cset209.png": "吸血喵喵酱",
  "f_cset210.png": "香榭黄昏套装",
  "f_cset211.png": "黑蝙蝠魔仙套装",
  "f_cset212.png": "樱红果酱短裙",
  "f_cset213.png": "雪夜金铃套装",
  "f_cset214.png": "沐雪晨曦套装",
  "f_cset215.png": "冰雪王女套装",
  "f_cset216.png": "晓美焰套装",
  "f_cset217.png": "温柔蔷薇女装",
  "f_cset218.png": "龙梅映雪",
  "f_cset219.png": "花枝纤纤",
  "f_cset220.png": "傲雪寒梅",
  "f_cset221.png": "螺钉布偶套装",
  "f_cset222.png": "凤冠霞帔套装",
  "f_cset223.png": "花开富贵套装",
  "f_cset2234.png": "时尚之汐女装",
  "f_cset224.png": "春漾玫瑰套装",
  "f_cset225.png": "冰霖寒雪套装",
  "f_cset227.png": "俄罗斯女装",
  "f_cset228.png": "霓裳羽衣",
  "f_cset229.png": "红色小披肩",
  "f_cset230.png": "夜魅套装",
  "f_cset231.png": "粉梦小熊套装",
  "f_cset232.png": "雪国公主套装",
  "f_cset233.png": "古韩女装",
  "f_cset234.png": "朵儿蓬蓬裙",
  "f_cset235.png": "囡囡布偶装",
  "f_cset236.png": "枯树女精灵",
  "f_cset237.png": "婵娟女儿装",
  "f_cset238.png": "意大利女装",
  "f_cset239.png": "街头女孩套装",
  "f_cset240.png": "魔法小巫套装",
  "f_cset241.png": "日式女古装",
  "f_cset242.png": "兜兜兔套装",
  "f_cset243.png": "夏日蓬蓬裙",
  "f_cset244.png": "薇纱恋语",
  "f_cset245.png": "童话梦洋装",
  "f_cset246.png": "百炼成仙女装",
  "f_cset247.png": "碎花背带裤",
  "f_cset248.png": "蓝梦星愿套装",
  "f_cset249.png": "埃及女装",
  "f_cset250.png": "十月粉粉裙",
  "f_cset251.png": "花国初秋",
  "f_cset252.png": "嫩芽女装",
  "f_cset253.png": "新星露肩装",
  "f_cset254.png": "鱼小姐套装",
  "f_cset255.png": "爱丽丝连身裙",
  "f_cset256.png": "巴西女装",
  "f_cset257.png": "万圣节夜宴套装",
  "f_cset258.png": "万圣节魅仆套装",
  "f_cset259.png": "性感女郎长裙",
  "f_cset260.png": "星梦娃娃装",
  "f_cset261.png": "街球啦啦队",
  "f_cset262.png": "兔小姐连身裙",
  "f_cset263.png": "泰式女装",
  "f_cset264.png": "舞会红裙摆",
  "f_cset265.png": "华丽女仆装",
  "f_cset266.png": "圣诞公主裙",
  "f_cset267.png": "熊熊布偶女装",
  "f_cset268.png": "金边铃铛裙",
  "f_cset269.png": "小棉袄圣诞裙",
  "f_cset270.png": "桃花侍女套装",
  "f_cset271.png": "幽紫缎带冬裙",
  "f_cset2719.png": "甜辣冬日女装",
  "f_cset272.png": "优雅刺绣套裙",
  "f_cset273.png": "加拿大女装",
  "f_cset274.png": "编织篮田园套裙",
  "f_cset275.png": "黑色喵喵套装",
  "f_cset276.png": "雨后女装",
  "f_cset277.png": "粉蔓花朵披肩裙",
  "f_cset278.png": "晚宴华丽舞裙",
  "f_cset279.png": "仙霞绸缎裙",
  "f_cset280.png": "恶魔邪魅套装",
  "f_cset281.png": "雪绒兔毛套装",
  "f_cset282.png": "小短衫拼接裙",
  "f_cset283.png": "娟秀女装",
  "f_cset284.png": "澳大利亚女装",
  "f_cset285.png": "缥帙交领襦裙",
  "f_cset286.png": "晚宴女王套裙",
  "f_cset287.png": "雪倾城长裙",
  "f_cset288.png": "路西菲尔的蛊惑礼服",
  "f_cset289.png": "仙灵女巫薇薇安纱裙",
  "f_cset290.png": "草莓糖糖蓬蓬裙",
  "f_cset291.png": "温暖冬幕风衣",
  "f_cset292.png": "韩式小狐仙短裙",
  "f_cset293.png": "花涧",
  "f_cset294.png": "黑色大丽花套装",
  "f_cset295.png": "蓝色圆舞曲长裙",
  "f_cset296.png": "法式女装",
  "f_cset297.png": "亚瑟王套装",
  "f_cset298.png": "安妮可可套装",
  "f_cset299.png": "清凉巴菲套装",
  "f_cset300.png": "琉璃兔套装",
  "f_cset301.png": "赤金萤火套装",
  "f_cset302.png": "倚虹学士服套装",
  "f_cset303.png": "新区女装",
  "f_cset304.png": "粉蔷薇婚纱",
  "f_cset305.png": "粉粉蛋糕泳裙",
  "f_cset306.png": "粉恐龙睡衣",
  "f_cset307.png": "candy粉裙套装",
  "f_cset308.png": "琴瑶织梦",
  "f_cset309.png": "月影浮生",
  "f_cset310.png": "可可甜心套装",
  "f_cset311.png": "踏云逐月",
  "f_cset312.png": "紫阳云裳",
  "f_cset313.png": "红袍牡丹套装",
  "f_cset314.png": "罗马女神",
  "f_cset315.png": "桃心粉狸套装",
  "f_cset316.png": "紫衫短裙",
  "f_cset317.png": "蔚蓝蓬蓬裙",
  "f_cset318.png": "沐翎兰馨",
  "f_cset319.png": "巫灵斗篷女",
  "f_cset320.png": "金扫冥巫",
  "f_cset321.png": "水晶糖套装",
  "f_cset322.png": "蕾丝长靴套装",
  "f_cset323.png": "西莉卡套装",
  "f_cset324.png": "天使之翼",
  "f_cset325.png": "骷髅露肩装",
  "f_cset326.png": "沉溪碧蝶",
  "f_cset327.png": "粉粉企鹅袄",
  "f_cset3276.png": "蜜糖之甜女装",
  "f_cset328.png": "冰雪镇女装",
  "f_cset329.png": "午后红茶",
  "f_cset330.png": "糖沁袄裙",
  "f_cset331.png": "落樱大振",
  "f_cset332.png": "甜点小姐",
  "f_cset333.png": "圣诞叮铃",
  "f_cset334.png": "王系女装",
  "f_cset335.png": "幸福女装",
  "f_cset336.png": "蓝樱夜梦套装",
  "f_cset3368.png": "甜心猫猫拳女装",
  "f_cset337.png": "拼布袄裙",
  "f_cset338.png": "星光小蘑女",
  "f_cset339.png": "樱桃子小姐",
  "f_cset340.png": "梦幻花都",
  "f_cset341.png": "丰收圣女装",
  "f_cset342.png": "宁静月华",
  "f_cset343.png": "洛可可礼裙",
  "f_cset344.png": "璨梦琉璃",
  "f_cset345.png": "皇后恋歌套装",
  "f_cset346.png": "发条娃娃套装",
  "f_cset347.png": "樱桃千层酥",
  "f_cset348.png": "藏蓝物语",
  "f_cset3489.png": "惬意一夏女装",
  "f_cset349.png": "焦糖玛奇朵",
  "f_cset350.png": "僵尸娃娃（女）",
  "f_cset351.png": "练白瑛套装",
  "f_cset352.png": "森林精灵",
  "f_cset353.png": "和风魅瞳",
  "f_cset354.png": "希尔维亚",
  "f_cset355.png": "海风醉人时装",
  "f_cset356.png": "花晨月夕",
  "f_cset357.png": "时间兔子",
  "f_cset358.png": "香草暮美人",
  "f_cset3582.png": "沁心夏日女装",
  "f_cset3589.png": "邂逅亚特兰女装",
  "f_cset359.png": "布偶拼接裙",
  "f_cset360.png": "金蝶舞衣",
  "f_cset361.png": "新手女装",
  "f_cset362.png": "梅落铅华长裙",
  "f_cset363.png": "曼妙罗衫",
  "f_cset364.png": "拼接复古斗篷装",
  "f_cset365.png": "星愿心语小洋装",
  "f_cset366.png": "星梦背带裙装",
  "f_cset367.png": "碧海银沙吊带裙",
  "f_cset368.png": "浪漫紫薰礼服",
  "f_cset369.png": "玉露香菱裙",
  "f_cset370.png": "向日葵娃娃领长裙",
  "f_cset371.png": "风情斜肩长裙",
  "f_cset3717.png": "精灵时花女装",
  "f_cset372.png": "仙飘飘复古长裙",
  "f_cset373.png": "阿拉丁套装",
  "f_cset3735.png": "酸奶不郁郁女装",
  "f_cset374.png": "芭芭拉古典长裙",
  "f_cset375.png": "热舞爱丽丝",
  "f_cset376.png": "铃兰高中女生",
  "f_cset377.png": "星月彩虹裙",
  "f_cset378.png": "米莉雅莉亚",
  "f_cset379.png": "蝙蝠铭文披风",
  "f_cset380.png": "恶魔宫廷百褶裙",
  "f_cset381.png": "纯情文艺女神",
  "f_cset382.png": "黑喵恶魔短裙",
  "f_cset383.png": "万圣节南瓜女装",
  "f_cset384.png": "花房姑娘连衣裙",
  "f_cset385.png": "深蓝风衣秋装",
  "f_cset386.png": "热舞学妹舞红裙",
  "f_cset387.png": "青涩爱恋公主裙",
  "f_cset388.png": "曲奇可可裙",
  "f_cset389.png": "爱丽丝扑克",
  "f_cset390.png": "迷彩服（矿洞）",
  "f_cset391.png": "迷彩服（丛林）",
  "f_cset392.png": "迷彩服（沙漠）",
  "f_cset393.png": "迷彩服（雪地）",
  "f_cset394.png": "雪狼贝贝",
  "f_cset3940.png": "恋感偶像女装",
  "f_cset395.png": "丹麦女装",
  "f_cset396.png": "清水芙蓉",
  "f_cset397.png": "圣诞女装",
  "f_cset398.png": "樱花少女时装",
  "f_cset399.png": "悠然飞絮套装",
  "f_cset400.png": "玛格丽特",
  "f_cset401.png": "世纪婚礼婚纱",
  "f_cset402.png": "爱伦古堡风衣",
  "f_cset403.png": "矿洞女（永久）",
  "f_cset404.png": "森林女（永久）",
  "f_cset405.png": "沙漠女（永久）",
  "f_cset406.png": "冰原女（永久）",
  "f_cset407.png": "流金岁月短裙",
  "f_cset408.png": "黄色猫咪玩偶装",
  "f_cset409.png": "萌萌兔女郎",
  "f_cset410.png": "莉莉娅的蝴蝶结",
  "f_cset411.png": "甜心蕾丝裙",
  "f_cset412.png": "武则天华服",
  "f_cset413.png": "名古屋新装",
  "f_cset414.png": "宝贝的布偶新衣",
  "f_cset415.png": "次元冷萌女装",
  "f_cset416.png": "穿越爱恋女装",
  "f_cset417.png": "完美新娘彩纱",
  "f_cset418.png": "魅影红玉女装",
  "f_cset4180.png": "红丝带蛋糕女装",
  "f_cset419.png": "战争之王长裙",
  "f_cset420.png": "红队女装",
  "f_cset421.png": "黄队女装",
  "f_cset422.png": "绿队女装",
  "f_cset423.png": "灰姑娘长裙",
  "f_cset424.png": "氧气连衣裙",
  "f_cset425.png": "纯爱洛丽塔裙装",
  "f_cset426.png": "灵风女装",
  "f_cset427.png": "挽月流霞长裙",
  "f_cset428.png": "春樱海滩女装",
  "f_cset429.png": "萌兔娃娃连衣裙",
  "f_cset430.png": "海湾恋人舞裙",
  "f_cset431.png": "花儿朵朵裙装",
  "f_cset432.png": "斯比套装（女）",
  "f_cset433.png": "九天美人女装",
  "f_cset434.png": "小可套装（女）",
  "f_cset435.png": "凤舞精灵女装",
  "f_cset436.png": "童心粉粉裙",
  "f_cset437.png": "暗金玫瑰舞裙",
  "f_cset438.png": "战争之王S2女装",
  "f_cset439.png": "梦心魔力裙",
  "f_cset440.png": "魔幻心灵裙",
  "f_cset441.png": "软心芭蕾裙",
  "f_cset442.png": "嘻哈兔妹",
  "f_cset443.png": "夏末轻纱裙",
  "f_cset444.png": "盛夏西瓜浴衣",
  "f_cset445.png": "盗墓大师魅魇套装",
  "f_cset446.png": "海浪沙滩比基尼",
  "f_cset447.png": "糖果甜心公主裙",
  "f_cset448.png": "树莓运动套装",
  "f_cset449.png": "白露为霜女装",
  "f_cset450.png": "南有乔木女装",
  "f_cset451.png": "天空之城天使套装",
  "f_cset452.png": "米洛洛波点裙",
  "f_cset453.png": "海的女儿美人鱼装",
  "f_cset454.png": "关关雎鸠女装",
  "f_cset455.png": "彼美孟姜女装",
  "f_cset456.png": "天竺少女",
  "f_cset457.png": "真真便服",
  "f_cset458.png": "紫夜凝香",
  "f_cset459.png": "格斗女狼",
  "f_cset460.png": "干物妹小埋套装",
  "f_cset461.png": "马卡龙糖果女装",
  "f_cset462.png": "灼灼其华女装",
  "f_cset463.png": "绿丝絺绤女装",
  "f_cset464.png": "青萝舞裙套装",
  "f_cset465.png": "江之岛盾子",
  "f_cset466.png": "红莓娃娃裙",
  "f_cset467.png": "小狸猫萝莉连衣裙",
  "f_cset468.png": "花月汉服女装",
  "f_cset469.png": "黑喵物语女装",
  "f_cset470.png": "小红帽套装",
  "f_cset471.png": "蓝蓝企鹅女装",
  "f_cset472.png": "旋转木马背带裙",
  "f_cset473.png": "小花仙连衣裙",
  "f_cset474.png": "星际王后晚礼服",
  "f_cset475.png": "邻家少女连衣裙",
  "f_cset476.png": "学院派舞会连衣裙",
  "f_cset477.png": "AH婚礼红毯礼服",
  "f_cset478.png": "南瓜公主舞裙",
  "f_cset479.png": "阿凡达女装",
  "f_cset480.png": "沁蓝舞裙",
  "f_cset481.png": "暗夜蔷薇",
  "f_cset483.png": "粉粉娃娃裙",
  "f_cset484.png": "蓝纱礼裙",
  "f_cset485.png": "咎儿女装",
  "f_cset486.png": "叮当圣诞装",
  "f_cset487.png": "神隐女装",
  "f_cset488.png": "水母女装",
  "f_cset489.png": "梦璃的童话梦",
  "f_cset490.png": "多尾凤蝶女套装",
  "f_cset491.png": "紫姬层叠礼裙",
  "f_cset492.png": "兔宝娃娃裙",
  "f_cset493.png": "红袄蓬蓬裙",
  "f_cset494.png": "粉色浪漫礼裙",
  "f_cset495.png": "蓝魅礼裙",
  "f_cset496.png": "古典深秋裙装",
  "f_cset497.png": "达达女装",
  "f_cset498.png": "奶油栗子",
  "f_cset499.png": "紫藤琉璃",
  "f_cset500.png": "童梦水手裙",
  "f_cset501.png": "圣诞冬袄裙",
  "f_cset503.png": "琼姿白梅舞",
  "f_cset504.png": "花园爱丽丝女装",
  "f_cset505.png": "暖秋披肩装",
  "f_cset506.png": "暖冬套装",
  "f_cset507.png": "新年玫瑰裙",
  "f_cset508.png": "粉粉熊围巾装",
  "f_cset509.png": "清凉小兔裙",
  "f_cset510.png": "巧克力糖果女装",
  "f_cset511.png": "猴猴暖冬裙",
  "f_cset512.png": "金桔蝴蝶裙",
  "f_cset513.png": "冰冻之心女装",
  "f_cset514.png": "星辰女装",
  "f_cset515.png": "波比兔家居女装",
  "f_cset516.png": "软软虎斑喵",
  "f_cset517.png": "毛绒粉粉裙",
  "f_cset518.png": "草莓甜心派女装",
  "f_cset519.png": "天使魔幻女装",
  "f_cset520.png": "羽毛婚纱",
  "f_cset521.png": "红锦鲤女装",
  "f_cset522.png": "战争之王S3女装",
  "f_cset524.png": "心舞会礼裙",
  "f_cset525.png": "红格子女装",
  "f_cset526.png": "甜蜜心情",
  "f_cset527.png": "宫廷萤光裙",
  "f_cset528.png": "粉飘飘连衣裙",
  "f_cset529.png": "紫色星星女装",
  "f_cset530.png": "红菱斗篷裙",
  "f_cset531.png": "冰雪少女",
  "f_cset532.png": "魅影女装",
  "f_cset533.png": "奥利奥女装",
  "f_cset534.png": "淡花女装",
  "f_cset535.png": "蓝意娃娃裙",
  "f_cset536.png": "棕色马甲套裙",
  "f_cset537.png": "粉粉熊婴儿装",
  "f_cset538.png": "恋恋魔法使女装",
  "f_cset539.png": "红色淑女女装",
  "f_cset540.png": "紫梦纱裙",
  "f_cset541.png": "蔷薇红莲裙",
  "f_cset542.png": "魔女之匙",
  "f_cset543.png": "暗紫小姐女装",
  "f_cset544.png": "紫夜歌女装",
  "f_cset545.png": "草莓棉花糖",
  "f_cset546.png": "撒豆鬼女装",
  "f_cset547.png": "樱之女巫",
  "f_cset548.png": "赤槿罗莎",
  "f_cset549.png": "曼舞轻姿",
  "f_cset550.png": "日系夏季女校服",
  "f_cset551.png": "木之本魔法兔女装",
  "f_cset552.png": "矢羽柄和服",
  "f_cset553.png": "小坏喵女装",
  "f_cset554.png": "玛丽亚",
  "f_cset555.png": "风铃套装",
  "f_cset556.png": "清灵荷韵女装",
  "f_cset557.png": "粉若满天星",
  "f_cset558.png": "乖巧小女仆女装",
  "f_cset559.png": "姜暮烟",
  "f_cset560.png": "小护士莉莉",
  "f_cset561.png": "清姿摇曳",
  "f_cset562.png": "听花女装",
  "f_cset563.png": "去春游女装",
  "f_cset564.png": "护士珍尼佛",
  "f_cset565.png": "粉粉企鹅",
  "f_cset566.png": "黑喵萌妹女装",
  "f_cset567.png": "时尚大方潮流装",
  "f_cset568.png": "乐高小象女装",
  "f_cset569.png": "蓝星粉粉女装",
  "f_cset570.png": "红色恋人女装",
  "f_cset571.png": "花季天空下的少女",
  "f_cset572.png": "时尚酷酷潮流装",
  "f_cset573.png": "薄荷香草裙裤装",
  "f_cset574.png": "初夏恋恋冰女装",
  "f_cset575.png": "栗栗熊熊女装",
  "f_cset576.png": "萌星星女装",
  "f_cset577.png": "安吉尔",
  "f_cset578.png": "秋月女裙",
  "f_cset579.png": "蓝色脉动女装",
  "f_cset580.png": "海洋泡沫女装",
  "f_cset581.png": "草莓裙",
  "f_cset582.png": "蓝莓裙",
  "f_cset583.png": "玻璃纱舞裙",
  "f_cset584.png": "兔子萝卜女装",
  "f_cset585.png": "月明星稀女装",
  "f_cset586.png": "十里暖风",
  "f_cset587.png": "静谧之狐女装",
  "f_cset588.png": "冰蓝鹿仙",
  "f_cset589.png": "静谧紫藤女装",
  "f_cset590.png": "花季少女女装",
  "f_cset591.png": "笛乐女装",
  "f_cset592.png": "一起兜兜风女装",
  "f_cset593.png": "南北极小洋装",
  "f_cset594.png": "波斯胡姬",
  "f_cset595.png": "鹏游蝶梦女装",
  "f_cset596.png": "晨星女装",
  "f_cset597.png": "瑰丽乐园女装",
  "f_cset598.png": "流光飞舞女装",
  "f_cset599.png": "气球喵女装",
  "f_cset600.png": "水果派对女装",
  "f_cset601.png": "朵蜜天女装",
  "f_cset602.png": "甜心小点",
  "f_cset603.png": "落樱缤纷",
  "f_cset604.png": "梦幻女装",
  "f_cset605.png": "牧羊女装",
  "f_cset606.png": "鲜花娘衣服",
  "f_cset607.png": "拉媞天女装",
  "f_cset608.png": "柯基泳圈女装",
  "f_cset609.png": "粉薇花仙女装",
  "f_cset610.png": "星幻女装",
  "f_cset611.png": "冰柠橘子女装",
  "f_cset612.png": "音乐课代表",
  "f_cset613.png": "南北极蝶舞女装",
  "f_cset614.png": "南北极豆花女装",
  "f_cset615.png": "南北极星点女装",
  "f_cset616.png": "南北极紫蝶女装",
  "f_cset617.png": "红衣佳人",
  "f_cset618.png": "乌丽女装",
  "f_cset619.png": "法苏天女女装",
  "f_cset620.png": "元气初秋女装",
  "f_cset621.png": "纤巧玉兔",
  "f_cset622.png": "勇圣女女装",
  "f_cset623.png": "仁圣女女装",
  "f_cset624.png": "啾啾阴阳师女装",
  "f_cset625.png": "琉金晚装",
  "f_cset626.png": "拉姆",
  "f_cset627.png": "蕾姆",
  "f_cset628.png": "瞌睡兔兔女装",
  "f_cset629.png": "萌心森林女装",
  "f_cset630.png": "天秤心语",
  "f_cset631.png": "蓝鲸女装",
  "f_cset632.png": "纡朱女装",
  "f_cset633.png": "智圣女女装",
  "f_cset634.png": "鲜花云朵女装",
  "f_cset635.png": "追风女装",
  "f_cset636.png": "捧花少女女装",
  "f_cset637.png": "戏水女装",
  "f_cset638.png": "南瓜蔷薇女巫",
  "f_cset639.png": "斯卡娣女装",
  "f_cset640.png": "塔娜托斯女装",
  "f_cset641.png": "爱蜜莉雅",
  "f_cset642.png": "紫流萤女装",
  "f_cset643.png": "樱花妹妹套装",
  "f_cset644.png": "天蝎物语女装",
  "f_cset645.png": "甜心花园女装",
  "f_cset646.png": "萌兔游乐园女装",
  "f_cset647.png": "摇滚小哈女装",
  "f_cset648.png": "云纱梦舞女裙",
  "f_cset649.png": "月如歌女装",
  "f_cset650.png": "天使恋之街女装",
  "f_cset651.png": "茸球拼色女装",
  "f_cset652.png": "冬雪恋歌女装",
  "f_cset654.png": "暖心温泉女装",
  "f_cset655.png": "驯鹿女装",
  "f_cset656.png": "流星天使女装",
  "f_cset657.png": "雪花蓬蓬女装",
  "f_cset658.png": "粉粉饭团面包服",
  "f_cset659.png": "精灵小猫咪",
  "f_cset660.png": "圣诞雪女装",
  "f_cset661.png": "冬季恋歌女装",
  "f_cset662.png": "梅子浆果裙",
  "f_cset663.png": "欢乐雪花女装",
  "f_cset664.png": "微笑扑克",
  "f_cset665.png": "冬日绵绵女装",
  "f_cset666.png": "冰晶女装",
  "f_cset667.png": "蝴蝶糖果泡泡裙",
  "f_cset668.png": "星愿幻梦女装",
  "f_cset669.png": "冬日暖阳女装",
  "f_cset670.png": "萌软软女装",
  "f_cset671.png": "软绵绵背带裤女装",
  "f_cset672.png": "小熊蜜糖女装",
  "f_cset673.png": "彩虹星星女装",
  "f_cset674.png": "梓心糖果女装",
  "f_cset675.png": "白白小天使",
  "f_cset676.png": "清爽格子女裙",
  "f_cset677.png": "草莓软心糖女装",
  "f_cset678.png": "水畔蓝花女装",
  "f_cset679.png": "鸟笼少女裙",
  "f_cset680.png": "噗噗小水壶",
  "f_cset681.png": "蝶恋花女装",
  "f_cset682.png": "十字路口女装",
  "f_cset683.png": "蝶絮纷飞女装",
  "f_cset684.png": "玫瑰心语女装",
  "f_cset685.png": "甜点水手裙",
  "f_cset686.png": "晴天茶会女装",
  "f_cset687.png": "恶魔娘服装",
  "f_cset688.png": "暖洋洋服装",
  "f_cset689.png": "蔓藤秋千",
  "f_cset690.png": "温暖泡泡浴（女）",
  "f_cset691.png": "叽叽叽女装",
  "f_cset693.png": "绿萝仙子",
  "f_cset694.png": "花嫁女装",
  "f_cset695.png": "鲜花球球女装",
  "f_cset696.png": "草莓软糖女装",
  "f_cset697.png": "萌兔学院裙",
  "f_cset698.png": "粉酥心晴女装",
  "f_cset699.png": "春季女校服",
  "f_cset700.png": "藤馨蔓蔓",
  "f_cset701.png": "喵咪蝴蝶结女装",
  "f_cset702.png": "迷森少女装",
  "f_cset703.png": "暗夜星辰女裙",
  "f_cset704.png": "纯白之春女装",
  "f_cset705.png": "马尔代夫女装",
  "f_cset706.png": "焦糖女装",
  "f_cset707.png": "森林谜纱女装",
  "f_cset708.png": "蛋糕派对纱裙女套装",
  "f_cset709.png": "糖果串珠裙",
  "f_cset710.png": "清心泉愿女装",
  "f_cset711.png": "草莓蛋糕女士睡袍",
  "f_cset712.png": "魔仙女王套装",
  "f_cset713.png": "软萌兔女装",
  "f_cset714.png": "紫月星宿女装",
  "f_cset715.png": "岚晶砂糖女装",
  "f_cset716.png": "波板糖甜心",
  "f_cset717.png": "绵绵兔几女装",
  "f_cset718.png": "糖果女孩套装",
  "f_cset719.png": "尤克里里女装",
  "f_cset720.png": "樱粉初春女装",
  "f_cset721.png": "春萌女装",
  "f_cset722.png": "心心新手服",
  "f_cset723.png": "街拍少女女装",
  "f_cset724.png": "噗噗围裙点心套装",
  "f_cset725.png": "星途长裙",
  "f_cset726.png": "雨中花园女装",
  "f_cset727.png": "星光魔术师女装",
  "f_cset728.png": "蓝色月光女装",
  "f_cset729.png": "可爱背包女装",
  "f_cset730.png": "湛蓝心情女装",
  "f_cset731.png": "淡色羽翼女装",
  "f_cset732.png": "金蝶女裙",
  "f_cset733.png": "蜜糖女装",
  "f_cset734.png": "一瞬永恒女装",
  "f_cset735.png": "软糖果果女装",
  "f_cset736.png": "蛋黄果酱女装",
  "f_cset737.png": "甜心背带装",
  "f_cset738.png": "小护士艾米",
  "f_cset739.png": "小护士迪希",
  "f_cset740.png": "优雅画框女装",
  "f_cset742.png": "旅行热气球女装",
  "f_cset743.png": "方糖咖啡女装",
  "f_cset744.png": "天蓝色的彼岸（女）",
  "f_cset745.png": "夏日优格女装",
  "f_cset746.png": "普罗旺斯女装",
  "f_cset747.png": "瞅你咋地！",
  "f_cset748.png": "水果硬糖女孩",
  "f_cset749.png": "节日气球女装",
  "f_cset750.png": "端午节女装",
  "f_cset751.png": "冰棱清凉女裙",
  "f_cset752.png": "叮铛茶花喵",
  "f_cset753.png": "紫堇云萝",
  "f_cset754.png": "克莉丝汀女装",
  "f_cset755.png": "草莓牛奶",
  "f_cset756.png": "假日沙滩女装",
  "f_cset757.png": "红色背带女装",
  "f_cset758.png": "鹦鹉背带裤（女）",
  "f_cset760.png": "叮当小兔女装",
  "f_cset761.png": "纯色花嫁女装",
  "f_cset762.png": "云端冰雪兔（女）",
  "f_cset763.png": "清新果茶女装",
  "f_cset764.png": "香橙蛋糕女装",
  "f_cset765.png": "零食大作战（女）",
  "f_cset766.png": "碧玉粉妆",
  "f_cset767.png": "薄荷小熊女装",
  "f_cset768.png": "炫彩涂鸦（女）",
  "f_cset769.png": "珍妮弗公主",
  "f_cset770.png": "晴天娃娃女装",
  "f_cset771.png": "卡拉赫拉公仔睡衣（女）",
  "f_cset772.png": "夏日旅行记女装",
  "f_cset773.png": "掰玉米女装",
  "f_cset774.png": "扑克兔女装",
  "f_cset775.png": "向日葵小熊（女）",
  "f_cset776.png": "星星泳圈女装",
  "f_cset777.png": "晴空海豚（女）",
  "f_cset778.png": "星草繁花女装",
  "f_cset779.png": "湛蓝花海女装",
  "f_cset780.png": "白猫女装",
  "f_cset781.png": "晴阳格子背带装（女）",
  "f_cset782.png": "蓝色玫瑰女装",
  "f_cset783.png": "绿藤花女裙",
  "f_cset784.png": "企鹅水手女装",
  "f_cset785.png": "沁凝西瓜裙",
  "f_cset786.png": "梦幻紫洋裙",
  "f_cset787.png": "蓝色海岸女装",
  "f_cset788.png": "绵绵雪糕女装",
  "f_cset789.png": "小青蛙格子装（女）",
  "f_cset790.png": "情书女装",
  "f_cset791.png": "梦幻婚纱礼裙",
  "f_cset792.png": "水果棒冰（女）",
  "f_cset793.png": "人鱼之恋女装",
  "f_cset794.png": "水果派女装",
  "f_cset795.png": "扇舞清云女装",
  "f_cset796.png": "兔兔蛋糕粉裙",
  "f_cset797.png": "吖吖女装",
  "f_cset798.png": "奶油糖女装",
  "f_cset799.png": "花好月圆女装",
  "f_cset800.png": "鲷鱼烧猫猫女装",
  "f_cset802.png": "小蘑菇女装",
  "f_cset803.png": "乐柠女装",
  "f_cset804.png": "雨神女装",
  "f_cset805.png": "粉晶水手裙",
  "f_cset808.png": "冰蓝玫瑰女装",
  "f_cset811.png": "单身汪女装",
  "f_cset813.png": "糖果派对女装",
  "f_cset815.png": "幸福沙漏女装",
  "f_cset817.png": "兔之旅程女装",
  "f_cset819.png": "下午茶女装",
  "f_cset820.png": "猫咪超市（女）",
  "f_cset821.png": "砂糖点心装（女）",
  "f_cset822.png": "霜糖蛋糕女装",
  "f_cset824.png": "花漫礼服女装",
  "f_cset826.png": "情窦初开女装",
  "f_cset828.png": "冷艳贵族女装",
  "f_cset829.png": "小恐龙睡衣（女）",
  "f_cset833.png": "星月女装",
  "f_cset835.png": "初冬校服女",
  "f_cset838.png": "企鹅背带裤（女）",
  "f_cset839.png": "秋日礼盒女装",
  "f_cset841.png": "南瓜晚会女装",
  "f_cset842.png": "赫赤蝙蝠女装",
  "f_cset847.png": "狐丸阴阳师女装",
  "f_cset849.png": "暮色森林女装",
  "f_cset853.png": "草莓巧克力棒女装",
  "f_cset857.png": "嘻嘻哈哈女装",
  "f_cset866.png": "纯白婚纱"
}
