{
  "m_hair001.png": "清爽OL",
  "m_hair002.png": "粉红小可爱",
  "m_hair003.png": "蝴蝶结",
  "m_hair004.png": "金色长发",
  "m_hair005.png": "清爽一夏",
  "m_hair006.png": "罗莉塔",
  "m_hair007.png": "邻家小妹",
  "m_hair008.png": "小丫头",
  "m_hair009.png": "崛起",
  "m_hair010.png": "粉紫",
  "m_hair011.png": "金色长发",
  "m_hair012.png": "银色卷发",
  "m_hair013.png": "黑色阳光发型",
  "m_hair014.png": "红色短发",
  "m_hair015.png": "蓝色短发",
  "m_hair016.png": "可爱短发",
  "m_hair017.png": "高贵金发",
  "m_hair018.png": "猫耳红色短发",
  "m_hair019.png": "绿色短发",
  "m_hair020.png": "咖啡色卷发",
  "m_hair022.png": "冒险家",
  "m_hair023.png": "俏皮小辫",
  "m_hair024.png": "浪漫一身",
  "m_hair025.png": "绿色小可爱",
  "m_hair026.png": "小红帽",
  "m_hair027.png": "飘逸长发",
  "m_hair028.png": "黄色运动服发型",
  "m_hair029.png": "女武神",
  "m_hair030.png": "路飞草帽",
  "m_hair031.png": "火影发型之鸣人",
  "m_hair032.png": "火影发型之佐助",
  "m_hair033.png": "火影发型之鹿丸",
  "m_hair034.png": "魔术女帽",
  "m_hair035.png": "女恶魔",
  "m_hair036.png": "粉色面罩",
  "m_hair037.png": "小鬼当家女帽",
  "m_hair038.png": "男生蓝色睡帽",
  "m_hair039.png": "黑龙发型",
  "m_hair040.png": "女美发师发型",
  "m_hair041.png": "铅笔头",
  "m_hair042.png": "书本头",
  "m_hair043.png": "楚楚动人",
  "m_hair044.png": "棕色花包头",
  "m_hair045.png": "黑色盘头",
  "m_hair046.png": "绿色偏马尾",
  "m_hair047.png": "粉色红头绳发型",
  "m_hair048.png": "清纯长发",
  "m_hair049.png": "紫色BOBO头",
  "m_hair050.png": "粉色棉花糖",
  "m_hair051.png": "清爽短发",
  "m_hair052.png": "成熟美",
  "m_hair054.png": "皇后金冠发型",
  "m_hair055.png": "织女发型",
  "m_hair056.png": "罗密欧发型",
  "m_hair057.png": "米奇红帽",
  "m_hair058.png": "泡泡青蛙",
  "m_hair059.png": "萝丝发型",
  "m_hair060.png": "樱发型",
  "m_hair061.png": "春丽发型",
  "m_hair062.png": "爱丽丝发型",
  "m_hair063.png": "神秘星占发型",
  "m_hair064.png": "俏皮青春女发型",
  "m_hair065.png": "糖心发型",
  "m_hair066.png": "粉色朋克短发",
  "m_hair067.png": "格格发型",
  "m_hair068.png": "金色绒绒发型",
  "m_hair069.png": "可爱花苞头",
  "m_hair070.png": "金色圣洁长发",
  "m_hair071.png": "金之舞动",
  "m_hair072.png": "金色风情卷发",
  "m_hair073.png": "芭比大小姐",
  "m_hair074.png": "清爽包包头",
  "m_hair075.png": "桃红短发",
  "m_hair076.png": "金色小天使",
  "m_hair077.png": "女扎库米发型",
  "m_hair078.png": "草莓樱樱",
  "m_hair079.png": "御姐银发",
  "m_hair080.png": "橙色咔哇",
  "m_hair081.png": "瑰红魔力",
  "m_hair082.png": "皮可红红",
  "m_hair083.png": "爆裂梦玛",
  "m_hair084.png": "高贵皇妃",
  "m_hair085.png": "梨花头",
  "m_hair086.png": "咪尔梦梦",
  "m_hair087.png": "布鲁喵喵",
  "m_hair088.png": "纽拉包包",
  "m_hair089.png": "金拉比",
  "m_hair090.png": "雅典娜",
  "m_hair091.png": "弥兰莎丽发型",
  "m_hair092.png": "雪比莉咪发型",
  "m_hair093.png": "波灵莉喵发型",
  "m_hair094.png": "吉拉宠宠发型",
  "m_hair095.png": "咕咕橙橙",
  "m_hair096.png": "尼嘟卷卷",
  "m_hair097.png": "兰蝶幻幻",
  "m_hair099.png": "梦蝶卷发",
  "m_hair100.png": "蓝星银发",
  "m_hair101.png": "红奇卷发",
  "m_hair102.png": "红红帽帽",
  "m_hair103.png": "青青绵绵发型",
  "m_hair104.png": "波喱发型",
  "m_hair1040.png": "彼岸男发",
  "m_hair105.png": "清凉短发",
  "m_hair106.png": "甜甜圈圈发型",
  "m_hair107.png": "天使发型",
  "m_hair108.png": "溜溜兔耳发型",
  "m_hair109.png": "拉丝金奇发型",
  "m_hair110.png": "冰冰卷发",
  "m_hair111.png": "草莓糖果金发",
  "m_hair112.png": "蝉月发型",
  "m_hair113.png": "绅士公主发型",
  "m_hair114.png": "萌动包包头",
  "m_hair115.png": "魔女银发",
  "m_hair1151.png": "雨落蛙蛙男发",
  "m_hair116.png": "缤纷星星卷发",
  "m_hair118.png": "鼓鼓白棉发",
  "m_hair119.png": "喜美绘心蓝",
  "m_hair120.png": "蝶曦曦",
  "m_hair121.png": "菲灵发型",
  "m_hair122.png": "圣圣南瓜发型",
  "m_hair123.png": "苏格兰卷卷",
  "m_hair124.png": "女包青天发型",
  "m_hair125.png": "女展昭发型",
  "m_hair126.png": "女张龙赵虎帽",
  "m_hair127.png": "女王朝马汉帽",
  "m_hair128.png": "女公孙策发型",
  "m_hair129.png": "米修嘭嘭发型",
  "m_hair130.png": "金克雷",
  "m_hair131.png": "女衙役发型",
  "m_hair132.png": "圣诞包包头",
  "m_hair1321.png": "狂奔猪猪男发",
  "m_hair133.png": "飘盈金丝发",
  "m_hair134.png": "莓莓蓝",
  "m_hair135.png": "卯兔财神女发型",
  "m_hair136.png": "莹之飘雪",
  "m_hair137.png": "卡咪梦露发型",
  "m_hair138.png": "花润发型",
  "m_hair139.png": "蓝莓芯长发",
  "m_hair140.png": "蛋糕卷卷",
  "m_hair141.png": "花花语长发",
  "m_hair142.png": "蓝幂金发",
  "m_hair143.png": "橘色玫瑰",
  "m_hair144.png": "春香发型",
  "m_hair145.png": "梅芳发型",
  "m_hair146.png": "秋菊发型",
  "m_hair1461.png": "奶昔泡泡男发",
  "m_hair147.png": "魅舞之影",
  "m_hair148.png": "樱花飘飘",
  "m_hair149.png": "咪乖猫猫发型",
  "m_hair150.png": "旗莎棕卷发",
  "m_hair151.png": "海盗少女发型",
  "m_hair152.png": "金色糖果发型",
  "m_hair153.png": "碧波长发",
  "m_hair154.png": "魔法少女发型",
  "m_hair155.png": "黄莺卷发",
  "m_hair156.png": "小熊灵动发型",
  "m_hair157.png": "蝴蝶结女发",
  "m_hair158.png": "梦露露",
  "m_hair159.png": "青青长发",
  "m_hair160.png": "天使之翼",
  "m_hair161.png": "莉莉小猫",
  "m_hair162.png": "蕾蕾娃娃头",
  "m_hair163.png": "星星麦穗头",
  "m_hair164.png": "蜜桃花蝴蝶",
  "m_hair165.png": "夜翼小魔女",
  "m_hair166.png": "芒果圣代",
  "m_hair167.png": "皮卡皮卡",
  "m_hair168.png": "爱音发型",
  "m_hair169.png": "海洋之心",
  "m_hair170.png": "萌萌头",
  "m_hair171.png": "球球猫",
  "m_hair172.png": "甜心兔",
  "m_hair1723.png": "粉裘枫糖男发",
  "m_hair173.png": "夏威夷露露",
  "m_hair174.png": "香芒橙子",
  "m_hair175.png": "香草薇琪",
  "m_hair176.png": "夏日花瓣",
  "m_hair177.png": "公主之心",
  "m_hair178.png": "蛋卷甜甜",
  "m_hair179.png": "朵朵小蜜蜂",
  "m_hair180.png": "魔光白雪",
  "m_hair181.png": "蔚蓝卷卷发",
  "m_hair182.png": "萤萤藤蔓",
  "m_hair183.png": "魔幻紫卷发",
  "m_hair184.png": "古典王姬",
  "m_hair186.png": "淡白小可爱",
  "m_hair187.png": "蓝帽小雨",
  "m_hair188.png": "苹果短发",
  "m_hair189.png": "日风樱花",
  "m_hair190.png": "糖糖兔发型",
  "m_hair191.png": "魔导小蝙蝠",
  "m_hair1911.png": "抱抱熊男发",
  "m_hair192.png": "哆哆拉魔女",
  "m_hair193.png": "草莓奶昔发型",
  "m_hair194.png": "飘蓝星星发型",
  "m_hair195.png": "夏香百合发型",
  "m_hair196.png": "天使之恋",
  "m_hair197.png": "女科学家发型",
  "m_hair198.png": "萝莉小星星",
  "m_hair199.png": "清凉运动短发",
  "m_hair200.png": "薄雾长发",
  "m_hair201.png": "牛仔金色长发",
  "m_hair2017.png": "心碎信号男发",
  "m_hair203.png": "墨绿复古长发",
  "m_hair204.png": "菇菇短发",
  "m_hair205.png": "棕色小玫瑰",
  "m_hair206.png": "桐乃金发",
  "m_hair207.png": "月影飞仙发型",
  "m_hair208.png": "蓝色雾气长发",
  "m_hair209.png": "冰晶长发",
  "m_hair210.png": "蔷薇长发",
  "m_hair211.png": "莉莉安长发",
  "m_hair212.png": "小樱桃长发",
  "m_hair213.png": "粉色空姐发型",
  "m_hair214.png": "白色洋洋发型",
  "m_hair215.png": "樱红棕色短发",
  "m_hair216.png": "南瓜糖果发型",
  "m_hair217.png": "安娜公主发型",
  "m_hair218.png": "海洋波浪长发",
  "m_hair219.png": "蓝色花语发型",
  "m_hair220.png": "金羽发型",
  "m_hair221.png": "喵喵酱发型",
  "m_hair222.png": "香榭发型",
  "m_hair223.png": "魔仙金发",
  "m_hair224.png": "果酱发型",
  "m_hair225.png": "金铃发型",
  "m_hair226.png": "晨曦发型",
  "m_hair227.png": "王女发型",
  "m_hair228.png": "晓美焰发型",
  "m_hair229.png": "温柔蔷薇女发",
  "m_hair230.png": "龙梅发型",
  "m_hair231.png": "纤纤发型",
  "m_hair232.png": "寒梅发型",
  "m_hair233.png": "布偶麻花辫",
  "m_hair2331.png": "时尚之汐男发",
  "m_hair234.png": "花开发型",
  "m_hair235.png": "春漾银发",
  "m_hair236.png": "寒雪发型",
  "m_hair237.png": "幸运四叶草发型",
  "m_hair238.png": "俄风女发",
  "m_hair239.png": "霓裳发型",
  "m_hair240.png": "粉翘翘发型",
  "m_hair241.png": "夜魅发型",
  "m_hair242.png": "粉梦发型",
  "m_hair243.png": "雪国公主发型",
  "m_hair244.png": "古韩女发",
  "m_hair245.png": "朵儿金发",
  "m_hair246.png": "囡囡麻花辫",
  "m_hair247.png": "精灵女发",
  "m_hair248.png": "沐兰婵娟女发",
  "m_hair249.png": "意式女发",
  "m_hair250.png": "蝴蝶结双马尾",
  "m_hair251.png": "卷卷蝴蝶结",
  "m_hair252.png": "绿野仙踪",
  "m_hair253.png": "粉色初恋",
  "m_hair254.png": "魔幻粉紫发型",
  "m_hair255.png": "殇涩回忆",
  "m_hair256.png": "樱雪纷飞",
  "m_hair257.png": "淡墨画情",
  "m_hair258.png": "泡沫之恋",
  "m_hair259.png": "日式女发",
  "m_hair260.png": "风儿轻扬",
  "m_hair261.png": "童话梦女发",
  "m_hair262.png": "百炼成仙女发",
  "m_hair263.png": "香橙卷卷",
  "m_hair264.png": "红白挑染",
  "m_hair265.png": "埃及女发",
  "m_hair266.png": "初秋金发",
  "m_hair267.png": "嫩芽花苞",
  "m_hair268.png": "新星女孩",
  "m_hair269.png": "翘翘鱼小姐",
  "m_hair270.png": "巴西女发",
  "m_hair271.png": "万圣节夜宴发型",
  "m_hair272.png": "万圣节魅仆发型",
  "m_hair273.png": "金色女郎发型",
  "m_hair274.png": "粉紫发髻",
  "m_hair275.png": "兔小姐金发",
  "m_hair276.png": "泰式女发",
  "m_hair277.png": "蓬蓬双马尾",
  "m_hair280.png": "绿叶精灵发型",
  "m_hair281.png": "侍女长发",
  "m_hair282.png": "金丽娜丝发型",
  "m_hair283.png": "加拿大女发",
  "m_hair284.png": "田园少女发型",
  "m_hair2847.png": "甜辣冬日男发",
  "m_hair285.png": "粉莹飞舞发型",
  "m_hair286.png": "恶魔银发",
  "m_hair287.png": "雪绒小发絮",
  "m_hair288.png": "绿绸带麻花辫",
  "m_hair289.png": "娟秀长发",
  "m_hair290.png": "宫廷秀女发型",
  "m_hair291.png": "澳大利亚女发",
  "m_hair292.png": "缥帙长发",
  "m_hair293.png": "晚宴女王短发",
  "m_hair294.png": "雪倾城长发",
  "m_hair295.png": "路西菲尔的蛊惑发型",
  "m_hair296.png": "仙灵女巫薇薇安发型",
  "m_hair297.png": "粉色包包头",
  "m_hair298.png": "草莓糖糖女发",
  "m_hair299.png": "花涧长发",
  "m_hair300.png": "韩式小狐仙长发",
  "m_hair301.png": "清凉盛夏女发",
  "m_hair302.png": "黑色大丽花发型",
  "m_hair303.png": "蓝色圆舞曲发型",
  "m_hair304.png": "法式女发",
  "m_hair305.png": "剑士发型",
  "m_hair306.png": "安妮金发",
  "m_hair307.png": "清凉盘发",
  "m_hair308.png": "奶油洛丽塔",
  "m_hair309.png": "香草可丽饼",
  "m_hair310.png": "玉子蛋筒",
  "m_hair311.png": "西柚双马尾",
  "m_hair312.png": "琉璃兔发型",
  "m_hair313.png": "白雪姬",
  "m_hair314.png": "雪洞鬼灯",
  "m_hair315.png": "我妻由乃",
  "m_hair316.png": "红玛利亚",
  "m_hair317.png": "萤火金发",
  "m_hair318.png": "倚虹学士发型",
  "m_hair319.png": "新区女装发型",
  "m_hair320.png": "粉蔷薇卷发",
  "m_hair321.png": "粉粉蛋糕发型",
  "m_hair322.png": "candy短发",
  "m_hair323.png": "织梦发型",
  "m_hair324.png": "浮生银发",
  "m_hair325.png": "可可花苞",
  "m_hair326.png": "踏云发型",
  "m_hair327.png": "紫阳发髻",
  "m_hair328.png": "牡丹发型",
  "m_hair329.png": "罗马女神红发",
  "m_hair330.png": "桃心银发",
  "m_hair331.png": "卷尾金发",
  "m_hair332.png": "兰馨发型",
  "m_hair333.png": "水晶金发",
  "m_hair334.png": "慕斯长发",
  "m_hair335.png": "西莉卡发型",
  "m_hair336.png": "粉粉天使",
  "m_hair337.png": "摇滚天后女发",
  "m_hair338.png": "碧蝶银发",
  "m_hair339.png": "粉企鹅小辫",
  "m_hair340.png": "冰雪女发",
  "m_hair341.png": "红茶发型",
  "m_hair342.png": "糖沁发型",
  "m_hair343.png": "浅金女发",
  "m_hair344.png": "叮铃发型",
  "m_hair345.png": "落樱发型",
  "m_hair346.png": "蓝樱夜梦发型",
  "m_hair347.png": "拼布盘发",
  "m_hair348.png": "小蘑女发型",
  "m_hair349.png": "彩虹兔（女）",
  "m_hair350.png": "古逸朱钗",
  "m_hair3502.png": "蜜糖之甜男发",
  "m_hair351.png": "韩式小揪揪",
  "m_hair352.png": "花苞妹",
  "m_hair353.png": "金倪蜜语",
  "m_hair354.png": "蓝雨暮光",
  "m_hair355.png": "梨花精灵",
  "m_hair356.png": "俏皮翠",
  "m_hair357.png": "樱桃子发型",
  "m_hair358.png": "花都发型",
  "m_hair359.png": "丰收祭祀女发",
  "m_hair3599.png": "甜心猫猫拳男发",
  "m_hair360.png": "月华女发",
  "m_hair361.png": "洛可可女发",
  "m_hair362.png": "璨梦发型",
  "m_hair363.png": "皇后恋歌发型",
  "m_hair364.png": "星星女发",
  "m_hair365.png": "发条娃娃发型",
  "m_hair366.png": "歌月流莹",
  "m_hair367.png": "樱桃发型",
  "m_hair368.png": "藏蓝女发",
  "m_hair369.png": "玛奇朵发型",
  "m_hair370.png": "僵尸女发",
  "m_hair371.png": "练白瑛发型",
  "m_hair372.png": "森林精灵卷发",
  "m_hair3724.png": "惬意一夏男发",
  "m_hair373.png": "蝴蝶结花苞女发",
  "m_hair374.png": "魅瞳脸谱女发",
  "m_hair375.png": "清新初夏",
  "m_hair376.png": "倾城记忆",
  "m_hair377.png": "时间兔子发型",
  "m_hair378.png": "桂子飘香发簪",
  "m_hair379.png": "布偶小野",
  "m_hair380.png": "轻舞飞扬",
  "m_hair381.png": "新手女发",
  "m_hair3816.png": "沁心夏日男发",
  "m_hair382.png": "恶魔蝴蝶结",
  "m_hair3825.png": "邂逅亚特兰男发",
  "m_hair383.png": "红梅傲雪",
  "m_hair384.png": "美国女发型",
  "m_hair385.png": "红簪发髻",
  "m_hair386.png": "紫罗兰复古盘发",
  "m_hair387.png": "浪漫花语",
  "m_hair388.png": "星愿心语",
  "m_hair389.png": "普罗旺斯之恋",
  "m_hair390.png": "星梦月明",
  "m_hair391.png": "碧海麻花",
  "m_hair392.png": "浪漫维他命",
  "m_hair393.png": "玉露云髻",
  "m_hair394.png": "热浪包子头",
  "m_hair395.png": "淡紫莹莹",
  "m_hair396.png": "蒂娜小熊",
  "m_hair397.png": "草色原野",
  "m_hair398.png": "软兔咩咩",
  "m_hair399.png": "小精灵",
  "m_hair400.png": "小巫仙",
  "m_hair401.png": "呆萌萝莉",
  "m_hair4015.png": "精灵时花男发",
  "m_hair402.png": "粉粉蝴蝶结",
  "m_hair403.png": "青藤初夏",
  "m_hair4035.png": "酸奶不郁郁男发",
  "m_hair404.png": "托帕",
  "m_hair405.png": "香草冰淇淋",
  "m_hair406.png": "馨色幻想",
  "m_hair407.png": "月光大波浪",
  "m_hair408.png": "淡紫旋花",
  "m_hair409.png": "麦穗灿灿",
  "m_hair410.png": "淡粉小酱",
  "m_hair411.png": "火炎雪",
  "m_hair412.png": "金桔柠檬",
  "m_hair413.png": "可爱棉絮",
  "m_hair414.png": "蜜桃狐",
  "m_hair415.png": "风情绿萝",
  "m_hair416.png": "莫斯小爱",
  "m_hair417.png": "木之誓",
  "m_hair418.png": "萝莉之心",
  "m_hair419.png": "纯梦",
  "m_hair420.png": "萌鬼来袭",
  "m_hair421.png": "水云小卷浪",
  "m_hair422.png": "园艺馨馨",
  "m_hair423.png": "青春无敌",
  "m_hair424.png": "小仙女",
  "m_hair4249.png": "恋感偶像男发",
  "m_hair425.png": "花仙",
  "m_hair426.png": "罗兰飘雪",
  "m_hair427.png": "萌兔铃铛",
  "m_hair428.png": "炫紫萝莉",
  "m_hair429.png": "忆纷飞",
  "m_hair430.png": "甜蜜心思",
  "m_hair432.png": "阿拉丁发型",
  "m_hair433.png": "英伦风情",
  "m_hair435.png": "热舞甜心",
  "m_hair436.png": "铃音少女",
  "m_hair437.png": "可爱萌主",
  "m_hair438.png": "星月彩虹发型",
  "m_hair439.png": "玲珑编发",
  "m_hair440.png": "蝙蝠王后",
  "m_hair441.png": "天使恶魔心",
  "m_hair442.png": "梦里年华",
  "m_hair443.png": "黑喵小姐",
  "m_hair444.png": "南瓜少女",
  "m_hair445.png": "花房姑娘",
  "m_hair446.png": "莹秋暖蓝",
  "m_hair447.png": "灵动青春",
  "m_hair448.png": "热舞甜心",
  "m_hair4489.png": "红丝带蛋糕男发",
  "m_hair449.png": "庆典狂欢兔",
  "m_hair450.png": "悠悠我心",
  "m_hair451.png": "银光女发",
  "m_hair452.png": "馨蓝茉莉",
  "m_hair453.png": "丹麦女发",
  "m_hair454.png": "时尚芭比",
  "m_hair455.png": "圣诞女发",
  "m_hair456.png": "朱丝麻花",
  "m_hair457.png": "云霞",
  "m_hair458.png": "樱花蝴蝶结",
  "m_hair459.png": "爱的朱丽叶",
  "m_hair460.png": "叶阑珊",
  "m_hair461.png": "世纪之约",
  "m_hair462.png": "古堡公主",
  "m_hair463.png": "流金岁月",
  "m_hair464.png": "黄色喵咪发型",
  "m_hair465.png": "童话兔兔",
  "m_hair466.png": "莉莉娅女郎",
  "m_hair467.png": "粉紫麻花小辫",
  "m_hair468.png": "次元冷萌女发",
  "m_hair469.png": "汤圆约会女发",
  "m_hair470.png": "穿越爱恋女发",
  "m_hair471.png": "完美新娘盘发",
  "m_hair472.png": "魅影红玉女发",
  "m_hair473.png": "战争之王女发",
  "m_hair474.png": "樱桃红红女发",
  "m_hair475.png": "春暖花开花苞头",
  "m_hair476.png": "活力萌妹发型",
  "m_hair477.png": "灰姑娘发型",
  "m_hair478.png": "氧气盘发",
  "m_hair479.png": "纯爱洛丽塔长发",
  "m_hair480.png": "灵风女发",
  "m_hair481.png": "挽月流霞女发",
  "m_hair482.png": "春樱海滩女发",
  "m_hair483.png": "萌兔娃娃发型",
  "m_hair484.png": "茶艺学童双马尾",
  "m_hair485.png": "海湾恋人女发",
  "m_hair486.png": "花儿朵朵发型",
  "m_hair487.png": "华尔兹女发",
  "m_hair488.png": "九天美人女发",
  "m_hair489.png": "凤舞精灵女发",
  "m_hair490.png": "暗金玫瑰发型",
  "m_hair491.png": "盛夏风情女发",
  "m_hair492.png": "橙馨微影",
  "m_hair493.png": "一菲发束",
  "m_hair494.png": "夏日迷情",
  "m_hair495.png": "战争之王S2女发",
  "m_hair496.png": "花玲珑",
  "m_hair497.png": "爱音恋夏",
  "m_hair498.png": "莫愁挑染女发",
  "m_hair499.png": "爱音漫卷",
  "m_hair500.png": "盛夏西瓜女发",
  "m_hair501.png": "海浪沙滩女发",
  "m_hair502.png": "糖果甜心女发",
  "m_hair503.png": "熊熊兔女发",
  "m_hair504.png": "树莓女发",
  "m_hair505.png": "白露为霜女发",
  "m_hair506.png": "南有乔木女发",
  "m_hair507.png": "魔法天使",
  "m_hair508.png": "米洛洛马尾",
  "m_hair509.png": "海的女儿",
  "m_hair510.png": "遥远星空女发",
  "m_hair511.png": "关关雎鸠女发",
  "m_hair512.png": "彼美孟姜女发",
  "m_hair513.png": "天竺女发",
  "m_hair514.png": "真真发型",
  "m_hair515.png": "紫夜凝香女发",
  "m_hair516.png": "格斗女发",
  "m_hair517.png": "星缘王后",
  "m_hair518.png": "糖果女发",
  "m_hair519.png": "高冷校花",
  "m_hair520.png": "灼灼其华女发",
  "m_hair521.png": "绿丝絺绤女发",
  "m_hair522.png": "青萝女发",
  "m_hair523.png": "江之岛女发",
  "m_hair524.png": "红莓女发",
  "m_hair525.png": "小狸猫萝莉女发",
  "m_hair526.png": "翠湖约会女发",
  "m_hair527.png": "花月女发",
  "m_hair528.png": "黑喵物语女发",
  "m_hair529.png": "小红帽女发",
  "m_hair530.png": "小红帽连帽短发",
  "m_hair531.png": "红颜知己女发",
  "m_hair532.png": "蓝企鹅女发",
  "m_hair533.png": "旋转木马女发",
  "m_hair534.png": "小花仙女发",
  "m_hair535.png": "星际王后长卷发",
  "m_hair536.png": "邻家少女发型",
  "m_hair537.png": "学院派舞会女发",
  "m_hair538.png": "AH婚礼红毯女发",
  "m_hair539.png": "南瓜公主发型",
  "m_hair540.png": "彩虹天堂",
  "m_hair541.png": "阿凡达女发",
  "m_hair542.png": "沁蓝女发",
  "m_hair543.png": "暗夜女发",
  "m_hair544.png": "冰蓝女发",
  "m_hair545.png": "春风男发",
  "m_hair546.png": "粉粉女发",
  "m_hair547.png": "蓝纱发型",
  "m_hair548.png": "咎儿女发",
  "m_hair549.png": "莫妮卡女发",
  "m_hair550.png": "叮当女发",
  "m_hair551.png": "神隐女发",
  "m_hair552.png": "水母女发",
  "m_hair553.png": "梦璃女发",
  "m_hair554.png": "彩虹咩女发",
  "m_hair555.png": "凤蝶女发",
  "m_hair556.png": "紫姬发型",
  "m_hair557.png": "兔宝发型",
  "m_hair558.png": "红袄发型",
  "m_hair559.png": "女王帅气的短发",
  "m_hair560.png": "蓝魅发型",
  "m_hair561.png": "拜占庭女发",
  "m_hair562.png": "古典深秋女发",
  "m_hair563.png": "美术课代表男发",
  "m_hair564.png": "红果果发型",
  "m_hair565.png": "黑色燕尾服女发",
  "m_hair566.png": "白梅发型",
  "m_hair567.png": "水手裙发型",
  "m_hair568.png": "花园爱丽丝女发",
  "m_hair569.png": "蓝色长发",
  "m_hair570.png": "夏末轻纱女发",
  "m_hair571.png": "魔幻心灵女发",
  "m_hair572.png": "软心芭蕾女发",
  "m_hair573.png": "嘻哈兔妹女发",
  "m_hair574.png": "紫藤琉璃女发",
  "m_hair575.png": "奶油栗子女发",
  "m_hair576.png": "露米娅",
  "m_hair577.png": "圣诞冬卷女发",
  "m_hair578.png": "红袄女发",
  "m_hair579.png": "新年玫瑰裙女发",
  "m_hair580.png": "巧克力糖果女发",
  "m_hair581.png": "冰冻之心女发",
  "m_hair582.png": "果茶女发",
  "m_hair583.png": "彩蝶萦绕女发",
  "m_hair584.png": "波比兔女发",
  "m_hair585.png": "虎斑喵女发",
  "m_hair586.png": "金桔女发",
  "m_hair587.png": "清凉兔女发",
  "m_hair588.png": "草莓甜心派女发",
  "m_hair589.png": "天使魔幻女发",
  "m_hair590.png": "红锦鲤女发",
  "m_hair591.png": "战争之王S3女发",
  "m_hair592.png": "猴猴暖冬女发",
  "m_hair593.png": "心舞会女发",
  "m_hair594.png": "锦葵紫女发",
  "m_hair595.png": "宫廷萌草女发",
  "m_hair596.png": "羽毛婚纱女发",
  "m_hair597.png": "心情女发",
  "m_hair598.png": "雅米女发",
  "m_hair599.png": "魅影女发",
  "m_hair601.png": "红菱女发",
  "m_hair602.png": "粉飘飘发型",
  "m_hair603.png": "冰雪少女发型",
  "m_hair604.png": "粉兔发型",
  "m_hair605.png": "毛绒粉粉女发",
  "m_hair606.png": "淡花女发",
  "m_hair607.png": "蓝意女发",
  "m_hair608.png": "金色双马尾",
  "m_hair609.png": "恋恋魔法使女发",
  "m_hair610.png": "哈莉奎因",
  "m_hair611.png": "朝阳淑女女发",
  "m_hair612.png": "星光女爵发型",
  "m_hair613.png": "冰蓝女发",
  "m_hair614.png": "草绿发辫",
  "m_hair615.png": "大蝴蝶结卷发",
  "m_hair616.png": "橘子汽水女发",
  "m_hair617.png": "蔷薇红莲女发",
  "m_hair618.png": "魔女女发",
  "m_hair619.png": "粉粉熊女发",
  "m_hair620.png": "莉紫女发",
  "m_hair621.png": "紫夜歌女发",
  "m_hair622.png": "风铃女发",
  "m_hair623.png": "撒豆鬼女发",
  "m_hair624.png": "樱之女巫发型",
  "m_hair625.png": "紫罗兰雨滴",
  "m_hair626.png": "泡沫蓝蔷薇",
  "m_hair627.png": "大道寺知世",
  "m_hair628.png": "日系蝴蝶结短发",
  "m_hair629.png": "紫色喵喵女发",
  "m_hair630.png": "玛丽亚之光",
  "m_hair631.png": "清灵荷韵女发",
  "m_hair632.png": "矢羽柄女发",
  "m_hair633.png": "满天星女发",
  "m_hair634.png": "俏皮丸子头",
  "m_hair635.png": "暮烟女发",
  "m_hair636.png": "莉莉的头发",
  "m_hair637.png": "草莓棉花糖女发",
  "m_hair638.png": "摇曳女发",
  "m_hair639.png": "听花女发",
  "m_hair641.png": "珍尼佛的金发",
  "m_hair642.png": "曼舞女发",
  "m_hair643.png": "银霜女发",
  "m_hair644.png": "时尚大方发型",
  "m_hair645.png": "乐高小象女发",
  "m_hair646.png": "蓝星粉粉女发",
  "m_hair647.png": "红茶女发",
  "m_hair648.png": "花季少女女发",
  "m_hair649.png": "时尚酷酷发型",
  "m_hair650.png": "薄荷香草女发",
  "m_hair651.png": "赤槿女发",
  "m_hair652.png": "初夏恋恋冰女发",
  "m_hair653.png": "栗栗熊熊女发",
  "m_hair654.png": "萌星星女发",
  "m_hair655.png": "安吉尔的金发",
  "m_hair656.png": "秋月女发",
  "m_hair657.png": "金色闪闪女发",
  "m_hair658.png": "海洋泡沫女发",
  "m_hair659.png": "草莓女发",
  "m_hair660.png": "蓝莓女发",
  "m_hair661.png": "兔子萝卜女发",
  "m_hair662.png": "月明星稀女发",
  "m_hair663.png": "暖风女发",
  "m_hair664.png": "静谧女发",
  "m_hair665.png": "仙鹿女发",
  "m_hair666.png": "静谧紫藤女发",
  "m_hair667.png": "花季少女女发",
  "m_hair668.png": "笛乐女发",
  "m_hair669.png": "一起兜兜风女发",
  "m_hair670.png": "南北极洋装女发",
  "m_hair671.png": "胡姬女发",
  "m_hair672.png": "鹏游蝶梦女发",
  "m_hair673.png": "晨星女发",
  "m_hair674.png": "瑰丽乐园女发",
  "m_hair675.png": "流光飞舞女发",
  "m_hair676.png": "气球喵女发",
  "m_hair677.png": "水果派对女发",
  "m_hair678.png": "朵蜜天女发型",
  "m_hair679.png": "甜心小点女发",
  "m_hair680.png": "落樱女发",
  "m_hair681.png": "梦幻星空女发",
  "m_hair682.png": "牧羊头发",
  "m_hair683.png": "鲜花头发",
  "m_hair684.png": "拉媞天女女发",
  "m_hair685.png": "柯基女发",
  "m_hair686.png": "粉薇花仙女发",
  "m_hair688.png": "冰柠橘子女发",
  "m_hair689.png": "音乐课代表女发",
  "m_hair691.png": "南北极豆花女发",
  "m_hair692.png": "南北极星点女发",
  "m_hair693.png": "南北极紫蝶女发",
  "m_hair694.png": "玻璃纱女发",
  "m_hair695.png": "朝与同歌",
  "m_hair696.png": "乌丽女发",
  "m_hair697.png": "法苏天女女发",
  "m_hair698.png": "元气初秋女发",
  "m_hair699.png": "玲珑女发",
  "m_hair700.png": "勇圣女女发",
  "m_hair701.png": "仁圣女女发",
  "m_hair702.png": "啾啾阴阳师女发",
  "m_hair703.png": "琉金女发",
  "m_hair705.png": "蕾姆发型",
  "m_hair706.png": "瞌睡兔兔女发",
  "m_hair707.png": "萌心森林女发",
  "m_hair708.png": "五星红发（女）",
  "m_hair709.png": "天秤心语女发",
  "m_hair710.png": "蓝鲸女发",
  "m_hair711.png": "纡朱女发",
  "m_hair712.png": "智圣女女发",
  "m_hair713.png": "鲜花云朵女发",
  "m_hair714.png": "追风女发",
  "m_hair715.png": "捧花少女女发",
  "m_hair716.png": "戏水女发",
  "m_hair717.png": "蓝莓软糖女发",
  "m_hair718.png": "南瓜蔷薇女发",
  "m_hair719.png": "斯卡娣女发",
  "m_hair720.png": "塔娜托斯女发",
  "m_hair721.png": "爱蜜女发",
  "m_hair722.png": "紫流萤女发",
  "m_hair723.png": "樱花妹妹发型",
  "m_hair724.png": "天蝎物语女发",
  "m_hair725.png": "甜心花园女发",
  "m_hair726.png": "摇滚小哈女发",
  "m_hair727.png": "萌兔游乐园女发",
  "m_hair728.png": "云纱梦舞女发",
  "m_hair729.png": "月如歌女发",
  "m_hair730.png": "天使恋之街女发",
  "m_hair731.png": "茸球发啾（女）",
  "m_hair732.png": "冬雪恋歌女发",
  "m_hair733.png": "花粉季节女发",
  "m_hair734.png": "暖心温泉女发",
  "m_hair735.png": "流星天使女发",
  "m_hair736.png": "雪花蓬蓬女发",
  "m_hair737.png": "粉粉饭团女发",
  "m_hair738.png": "精灵猫女发",
  "m_hair739.png": "圣诞雪女发",
  "m_hair740.png": "冬季恋歌女发",
  "m_hair741.png": "梅子浆果女发",
  "m_hair742.png": "欢乐雪花女发",
  "m_hair743.png": "扑克女发",
  "m_hair744.png": "冬日绵绵女发",
  "m_hair745.png": "冰晶女发",
  "m_hair746.png": "蝴蝶糖果女发",
  "m_hair747.png": "星愿幻梦女发",
  "m_hair748.png": "冬日暖阳女发",
  "m_hair749.png": "萌软软女发",
  "m_hair750.png": "软绵绵女发",
  "m_hair751.png": "小熊蜜糖女发",
  "m_hair752.png": "彩虹星星女发",
  "m_hair753.png": "莉莉的头发（紫色）",
  "m_hair754.png": "天使街女发（金色）",
  "m_hair755.png": "骄阳如歌",
  "m_hair756.png": "浪漫小鸠",
  "m_hair757.png": "犬神女发",
  "m_hair758.png": "梓心糖果女发",
  "m_hair760.png": "白白小天使女发",
  "m_hair761.png": "草莓软心糖女发",
  "m_hair762.png": "水畔蓝花女发",
  "m_hair763.png": "鸟笼女发",
  "m_hair764.png": "噗噗女发",
  "m_hair765.png": "蝶恋花女发",
  "m_hair766.png": "十字路口女发",
  "m_hair767.png": "蝶絮纷飞女发",
  "m_hair768.png": "玫瑰心语女发",
  "m_hair769.png": "甜点女发",
  "m_hair770.png": "晴天茶会女发",
  "m_hair773.png": "蔓藤女发",
  "m_hair774.png": "棒棒糖女发",
  "m_hair776.png": "粉沁女发",
  "m_hair922.png": "嘻嘻哈哈男发",
  "m_hair936.png": "纯白礼服男发"
}