{
  "m_bear001.png": {
    "name": "一字胡",
    "hideBaseLayer": false
  },
  "m_bear002.png": {
    "name": "络腮胡",
    "hideBaseLayer": false
  },
  "m_bear003.png": {
    "name": "圆胡",
    "hideBaseLayer": false
  },
  "m_bear004.png": {
    "name": "山羊胡",
    "hideBaseLayer": false
  },
  "m_bear005.png": {
    "name": "棕色山羊胡",
    "hideBaseLayer": false
  },
  "m_bear006.png": {
    "name": "关公美髯",
    "hideBaseLayer": false
  },
  "m_bear007.png": {
    "name": "白胡子",
    "hideBaseLayer": false
  },
  "m_bear008.png": {
    "name": "马里奥胡子",
    "hideBaseLayer": false
  },
  "m_bear009.png": {
    "name": "鬓角胡",
    "hideBaseLayer": false
  },
  "m_bear010.png": {
    "name": "大胡子",
    "hideBaseLayer": false
  },
  "m_bear011.png": {
    "name": "满脸胡茬子",
    "hideBaseLayer": false
  },
  "m_bear012.png": {
    "name": "白色长胡须",
    "hideBaseLayer": false
  }
}
